{"cameraMode":{"drawMode":0,"name":"Shaded","section":"Shading Mode"},"sceneLighting":true,"audioPlay":false,"sceneViewState":{"showFog":true,"showMaterialUpdate":false,"showSkybox":true,"showFlares":true,"showImageEffects":true,"showParticleSystems":true},"in2DMode":false,"pivot":{"x":29.45684814453125,"y":12.338077545166016,"z":-55.64032745361328},"rotation":{"x":-0.18638373911380769,"y":0.09267453849315644,"z":-0.019488584250211717,"w":-0.9782548546791077},"size":21.137893676757814,"orthographic":false}